{
  "id": 10149,
  "name": "Track Marketing Channel Performance with HighLevel, Google Sheets, and Slack",
  "description": "Description:\nDiscover which marketing channels actually convert with this n8n automation template.\n The workflow fetches all opportunities from HighLevel (GHL), filters for “Closed Won” deals, computes lead-to-sale conversion metrics per source, and sends a summary report to Slack while logging raw data into Google Sheets for ongoing analysis.\nPerfect for marketing teams, growth analysts, and sales managers who want to reduce wasted ad spend and double down on sources that deliver real ROI.\n\n✅ What This Template Does (Step-by-Step)\n⚡ Manual or Scheduled Trigger\n Run the workflow manually for instant analysis or automate it daily/weekly with a schedule trigger.\n📥 Fetch All Opportunities from HighLevel\n Pulls every deal record from your GHL CRM, including status, amount, and lead source fields.\n🔍 Filter for Closed-Won Deals\n Separates deals by outcome — only “Won” deals are used for conversion tracking, while others trigger Slack alerts for team review.\n📊 Log Won Deals to Google Sheets\n Saves every successful deal’s details into a structured Google Sheet for long-term performance tracking.\n🧮 Calculate Lead Source Metrics\n Aggregates results by lead source, calculating total deals, conversion rate, and total revenue per source automatically.\n📢 Send Slack Summary Report\n Posts a neat summary of conversion metrics to a dedicated Slack channel like #lead-source-report, ensuring visibility for the marketing and sales teams.\n🔔 Alert for Lost/Pending Deals\n Non-won opportunities are flagged and shared with the team via Slack for timely follow-ups.\n\n##🧠 Key Features\n 📊 Automated lead source performance tracking\n 💬 Slack alerts for both success and loss updates\n 📈 Real-time conversion and ROI visibility\n ⚙️ Seamless GHL + Google Sheets + Slack integration\n 🔁 Ready to run on-demand or on schedule\n\n💼 Use Cases\n 💡 Measure campaign ROI across channels\n 🎯 Identify top-performing ad platforms\n 📢 Send weekly sales source reports to marketing\n 💰 Optimize budget allocation using data-driven insights\n\n📦 Required Integrations\nHighLevel (GHL) – for opportunity data retrieval\nGoogle Sheets – for storing and visualizing deal data\nSlack – for team notifications and reports\n\n🎯 Why Use This Template?\n ✅ Saves hours of manual reporting work\n ✅ Ensures consistent performance tracking\n ✅ Highlights winning and underperforming sources\n ✅ Helps marketing teams focus on what truly converts\n",
  "nodes": [
    "n8n-nodes-base.googleSheets",
    "n8n-nodes-base.slack",
    "n8n-nodes-base.highLevel"
  ],
  "tags": []
}