{
  "id": 12083,
  "name": "Google Calendar Automated Notifications with Email, SMS & Analytics Dashboard",
  "description": "Automatically turn your Google Calendar into a fully-automated notification system with email alerts, SMS reminders, and a live performance dashboard - all powered by n8n.\n\nThis automation helps you never miss an event, while giving you clear visibility into what notifications were sent, when, and how reliably they ran.\n\nWhat This Automation Does\n\nThis solution is built as 4 connected workflows that run on a schedule and work together:\n\n1. Daily Email Summary (Morning)\n\nEvery morning, the workflow:\n\nReads today’s events from Google Calendar\n\nFormats them into a clean email\n\nSends a daily schedule summary via Mailchimp or SendGrid\n\n2. Daily SMS Summary\n\nShortly after, it:\n\nSends a concise SMS overview of today’s meetings using Twilio\n\n3. 15-Minute Event Reminders\n\nBefore each event:\n\nSends an individual SMS reminder\n\nSkips all-day events automatically\n\n4. Weekly Schedule Preview\n\nEvery Sunday:\n\nSends a week-ahead summary so you can plan in advance\n\nLive Reporting & Dashboard\n\nAll workflow activity is logged automatically into Google Sheets, which powers a real-time analytics dashboard showing:\n\nNumber of notifications sent\n\nSuccess vs failure rates\n\nDaily and weekly execution stats\n\nVisual charts powered by Chart.js\n\nNo manual tracking needed, everything updates automatically.\n\nHow the Workflow Is Structured\n\nThe automation is grouped into 3 clear sections:\n\nSection 1: Calendar Data Collection\n\nPulls events from Google Calendar\n\nFilters relevant meetings\n\nPrepares clean event data\n\nSection 2: Notifications & Messaging\n\nFormats emails and SMS messages\n\nSends reminders and summaries\n\nHandles scheduling logic\n\nSection 3: Logging & Reporting\n\nSaves every execution to Google Sheets\n\nUpdates daily stats automatically\n\nFeeds the live dashboard\n\nSUPPORT & FEEDBACK\nQuestions or issues? Connect with me on LinkedIn\nWant to see it in action? Try the live report demo: Click here\n",
  "nodes": [
    "n8n-nodes-base.googleSheets",
    "n8n-nodes-base.twilio",
    "n8n-nodes-base.mailchimp",
    "n8n-nodes-base.googleCalendar",
    "n8n-nodes-base.sendGrid",
    "n8n-nodes-base.code"
  ],
  "tags": []
}