{
  "id": 5307,
  "name": "AI Audio Transcription & Google Docs Report Generator with VLM Run",
  "description": "Automatically transform audio files into professional transcription reports with AI-powered speech recognition, timestamp generation, and formatted Google Docs output.\n\nWhat this workflow does\nMonitors Gmail for incoming audio attachments\nDownloads and processes audio files using VLM Run AI transcription\nGenerates accurate transcriptions with precise timestamps and segmentation\nCreates professional reports in Google Docs with formatted output\nHandles asynchronous processing for long audio files without timeouts\n\nSetup\nPrerequisites: Gmail account, VLM Run API credentials, Google Docs access, n8n.\n\nInstall the verified VLM Run node by searching for VLM Run in the node list, then click Install. Once installed, you can start using it in your workflows.\n\nQuick Setup:\nConfigure Gmail OAuth2 for email monitoring\nAdd VLM Run API credentials for audio transcription\nSet up Google Docs OAuth2 for report generation\nCreate target Google Doc for transcription reports\nUpdate document URL in workflow nodes\nTest with sample audio file and activate\n\nPerfect for\nMeeting recordings and conference calls\nVoice memos and dictation workflows\nInterview transcriptions and journalism\nPodcast episode documentation\nAccessibility compliance and documentation\nLegal proceedings and court recordings\nEducational content and lecture notes\nCustomer service call analysis\n\nKey Benefits\nHuman-level accuracy** - Advanced AI speech recognition with automatic punctuation\nTimestamp precision** - Segmented transcriptions with exact time markers\nMulti-format support** - Handles MP3, WAV, M4A, AAC, OGG, FLAC files\nAsynchronous processing** - No timeouts for long audio files\nProfessional formatting** - Beautifully structured Google Docs reports\nAutomatic workflow** - Zero manual intervention required\nSaves hours per recording** - Transforms manual transcription into instant results\nSearchable documentation** - Google Docs integration enables easy content discovery\n\nHow to customize\nExtend by adding:\nSpeaker identification and diarization\nIntegration with project management tools (Notion, Asana, Trello)\nAutomatic summary generation from transcripts\nTranslation to multiple languages\nSlack notifications for completed transcriptions\nIntegration with CRM systems for call logging\nAudio quality enhancement preprocessing\nCustom formatting templates for different use cases\nAutomatic keyword extraction and tagging\nIntegration with calendar systems for meeting context\n\nThis workflow revolutionizes audio documentation by combining cutting-edge AI transcription with professional report generation, making spoken content instantly accessible, searchable, and shareable across your organization.",
  "nodes": [
    "n8n-nodes-base.googleDocs"
  ],
  "tags": []
}