{
  "id": 5503,
  "name": "Automated Zoho Inventory to Supabase Product Data Pipeline",
  "description": "Description\n\nThis powerful n8n automation template enables seamless synchronization between Zoho Inventory and Supabase—keeping your product database up to date with zero manual effort. Whether you’re running an eCommerce store, inventory dashboard, or product catalog app, this workflow ensures your data pipeline stays clean, consistent, and fully automated.\n\nWhat This Template Does:\n\n🔁 Runs on a schedule to fetch inventory data from Zoho\n🔓 Authenticates via OAuth using refresh token for secure API access\n📦 Fetches products & variants with complete metadata\n🔄 Splits each item and maps it into Supabase row-by-row\n📊 Pushes rich product data, including name, SKU, unit, tags, stock levels, dimensions, and up to 3 custom attributes\n\nFields Included in Sync:\n\nProduct ID, Variant ID, Variant Name, Brand, SKU\nReturnability, Item Type, Unit, Attributes (1–3)\nTags, Stock on Hand, UPC/EAN/ISBN, Status\nReorder Level, Dimensions, Created Time, and more\n\nRequirements:\nZoho Inventory API access (with Refresh Token)\nSupabase account & API key\nTarget table (e.g., Fairy Frills) set up in Supabase\nOptional: Custom field mapping for additional use cases\n\nPerfect For:\n\nInventory managers syncing Zoho to custom dashboards\nD2C brands and eCommerce platforms powered by Supabase\nInternal tooling teams needing a real-time product database sync\nStartups replacing spreadsheets with a production-grade backend\n",
  "nodes": [
    "n8n-nodes-base.httpRequest",
    "n8n-nodes-base.supabase"
  ],
  "tags": []
}