{
  "id": 11663,
  "name": "Template-Based Google Drive Folder Generation with Forms and Apps Script",
  "description": "Overview\nStop manually creating folder structures for every new client or project. This workflow provides a simple form where users enter a name, and automatically duplicates your template folder structure in Google Drive—replacing all placeholders with the submitted name.\n\nWhat This Workflow Does\nDisplays a form where users enter a name (client, project, event, etc.)\nCreates a new main folder in Google Drive\nCalls Google Apps Script to duplicate your entire template structure\nReplaces all {{NAME}} placeholders in files and folder names\n\nKey Features\nSimple form interface** — No technical knowledge required to use\nRecursive duplication** — Copies all subfolders and files\nSmart placeholders** — Automatically replaces {{NAME}} everywhere\nProduction-ready** — Works immediately after setup\n\nPrerequisites\nGoogle Drive account with OAuth2 credentials in n8n\nGoogle Apps Script deployment (code below)\nTemplate folder in Drive using {{NAME}} as placeholder\n\nSetup\n\nStep 1: Create your template folder\n📁 {{NAME}} - Project Files\n├── 📁 01. {{NAME}} - Documents\n├── 📁 02. {{NAME}} - Assets\n├── 📁 03. Deliverables\n└── 📄 {{NAME}} - Brief.gdoc\n\nStep 2: Deploy Apps Script\nGo to script.google.com\nCreate new project → Paste code below\nDeploy → New deployment → Web app\nExecute as: Me | Access: Anyone\nCopy the deployment URL\n\nStep 3: Configure workflow\nReplace these placeholders:\nDESTINATION_PARENT_FOLDER_ID — Where new folders are created\nYOUR_APPS_SCRIPT_URL — URL from Step 2\nYOUR_TEMPLATE_FOLDER_ID — Folder to duplicate\n\nStep 4: Test\nActivate workflow → Open form URL → Submit a name → Check Drive!\n\nApps Script Code\n\nfunction doPost(e) {\n  try {\n    var params = e.parameter;\n    var templateFolderId = params.templateFolderId;\n    var name = params.name;\n    var destinationFolderId = params.destinationFolderId;\n    \n    if (!templateFolderId || !name) {\n      return jsonResponse({\n        success: false,\n        error: 'Missing required parameters: templateFolderId and name are required'\n      });\n    }\n    \n    var templateFolder = DriveApp.getFolderById(templateFolderId);\n    \n    if (destinationFolderId) {\n      var destinationFolder = DriveApp.getFolderById(destinationFolderId);\n      copyContentsRecursively(templateFolder, destinationFolder, name);\n      \n      return jsonResponse({\n        success: true,\n        id: destinationFolder.getId(),\n        url: destinationFolder.getUrl(),\n        name: destinationFolder.getName(),\n        mode: 'copied_to_existing',\n        timestamp: new Date().toISOString()\n      });\n    } else {\n      var parentFolder = templateFolder.getParents().next();\n      var newFolderName = replacePlaceholders(templateFolder.getName(), name);\n      var newFolder = parentFolder.createFolder(newFolderName);\n      copyContentsRecursively(templateFolder, newFolder, name);\n      \n      return jsonResponse({\n        success: true,\n        id: newFolder.getId(),\n        url: newFolder.getUrl(),\n        name: newFolder.getName(),\n        mode: 'created_new',\n        timestamp: new Date().toISOString()\n      });\n    }\n  } catch (error) {\n    return jsonResponse({\n      success: false,\n      error: error.toString()\n    });\n  }\n}\n\nfunction replacePlaceholders(text, name) {\n  var result = text;\n  result = result.replace(/\\{\\{NAME\\}\\}/g, name);\n  result = result.replace(/\\{\\{name\\}\\}/g, name.toLowerCase());\n  result = result.replace(/\\{\\{Name\\}\\}/g, name);\n  return result;\n}\n\nfunction copyContentsRecursively(sourceFolder, destinationFolder, name) {\n  var files = sourceFolder.getFiles();\n  while (files.hasNext()) {\n    try {\n      var file = files.next();\n      var newFileName = replacePlaceholders(file.getName(), name);\n      file.makeCopy(newFileName, destinationFolder);\n      Utilities.sleep(150);\n    } catch (error) {\n      Logger.log('Error copying file: ' + error.toString());\n    }\n  }\n  \n  var subfolders = sourceFolder.getFolders();\n  while (subfolders.hasNext()) {\n    try {\n      var subfolder = subfolders.next();\n      var newSubfolderName = replacePlaceholders(subfolder.getName(), name);\n      var newSubfolder = destinationFolder.createFolder(newSubfolderName);\n      Utilities.sleep(200);\n      copyContentsRecursively(subfolder, newSubfolder, name);\n    } catch (error) {\n      Logger.log('Error copying subfolder: ' + error.toString());\n    }\n  }\n}\n\nfunction jsonResponse(data) {\n  return ContentService\n    .createTextOutput(JSON.stringify(data))\n    .setMimeType(ContentService.MimeType.JSON);\n}\n\nUse Cases\nAgencies** — Client folder structure on new signup\nFreelancers** — Project folders from intake form\nHR Teams** — Employee onboarding folders\nSchools** — Student portfolio folders\nEvent Planners** — Event documentation folders\n\nNotes\nApps Script may take +60 seconds for large structures\nTimeout is set to 5 minutes for complex templates\nYour Google account needs edit access to template and destination folders",
  "nodes": [
    "n8n-nodes-base.httpRequest",
    "n8n-nodes-base.googleDrive"
  ],
  "tags": []
}