{
  "id": 11928,
  "name": "Automated CRM Enrichment: Enrich HubSpot Companies with CompanyEnrich",
  "description": "This n8n template automatically enriches company records in your CRM using CompanyEnrich and keeps your data up to date without manual work.\n\nThis workflow is ideal for RevOps, Sales Ops, and GTM teams who want cleaner CRM data for segmentation, scoring, and outbound workflows.\n\nGood to know\nCompany enrichment is performed by domain, so a valid company domain is required.\nThe template includes HubSpot, Salesforce, and Close CRM paths. Disable the CRM nodes you don’t use and remove their connection into the Extract Domain node.\nThe workflow processes companies in batches to avoid rate limits.\nEnrichment is only applied when the API request is successful.\n\nHow it works\nA Schedule Trigger runs the workflow on a recurring basis (weekly by default).\nExtracts the domain seeds of the companies for CompanyEnrich enrichment API. Pulls companies from:\nHubSpot: accounts created/updated within the time window (and can fetch full records if needed)\nSalesforce: accounts created/updated within the time window (and can fetch full records if needed)\nClose CRM: leads created within the time window via the Close search endpoint\nThe company domain is safely extracted, even if stored in different fields.\nEach domain is sent to the CompanyEnrich enrichment API.\nThe workflow checks whether the enrichment request was successful.\nEnriched data is mapped into HubSpot-compatible fields.\nThe corresponding HubSpot company record is updated.\nThe workflow continues looping until all companies are processed.\n\nHow to use\nHubSpot\nCreate a HubSpot private app with Company read + write scopes.\nAdd your HubSpot credentials to the HubSpot nodes (get companies + update company).\n\nSalesforce\nConnect your Salesforce account on all Salesforce nodes used in the workflow.\n\nClose CRM\nIn the Close CRM node, create a Basic Auth credential.\nPut your Close CRM API key in the username field.\nAppend a colon: to the end of the API key.\nLeave the password field empty. ⚠️ Important: If you don’t add: and keep password blank, authentication will fail.\nAdd your CompanyEnrich API key as an HTTP credential.\nAdjust the schedule if you want the workflow to run daily or on-demand.\nMake sure your HubSpot companies have a domain set.\nOnce active, the workflow will keep your company data enriched automatically.\n\nRequirements\nCompanyEnrich API key\nn8n instance with HTTP Request node enabled\nAt least one CRM connection:\nHubSpot private app token, or\nSalesforce OAuth, or\nClose CRM API key (Basic Auth with : rule)\n\nCustomising this workflow\nChange the schedule to run more frequently or trigger via webhook.\nAdd filters to enrich only specific company segments or pipelines.\nMap additional enriched fields to custom HubSpot properties.",
  "nodes": [
    "n8n-nodes-base.httpRequest",
    "n8n-nodes-base.hubspot",
    "n8n-nodes-base.salesforce"
  ],
  "tags": []
}