{
  "id": 13809,
  "name": "Run Hugging Face open-source AI models via webhook in n8n",
  "description": "This workflow connects n8n to the Hugging Face Inference API, letting you run powerful open-source AI models for text generation, summarization, sentiment analysis, translation, and image generation — all fully automated, no GPU setup required. Simply POST a request and get AI-powered results back in seconds.\n\nWhat's the Goal?\nTo give developers, agencies, and businesses a plug-and-play automation for running any Hugging Face model without managing infrastructure. Replace expensive proprietary APIs with open-source alternatives that you control.\n\nTasks this workflow handles out of the box:\nText generation (GPT-style content writing)\nSummarization (condense long documents)\nSentiment analysis (classify tone of any text)\nTranslation (multilingual content)\nImage generation (text-to-image via Stable Diffusion)\n\nWhy Does It Matter?\nHugging Face hosts over 400,000 open-source models — many matching or exceeding the quality of paid APIs at a fraction of the cost. This workflow:\n\nSaves money: free tier available, paid plans start at $9/mo\nGives full control: swap any model by changing one field\nScales instantly: no GPU provisioning or DevOps needed\nWorks in automation: connects to any n8n trigger or pipeline\nProduces billable output: agencies can resell AI services built on this\n\nHow It Works\nStep 1 — Webhook receives the task request with input text and task type\nStep 2 — Set node stores your Hugging Face API key and normalizes all inputs\nStep 3 — Code node selects the right model and builds the correct API payload for the task\nStep 4 — HTTP Request calls the Hugging Face Inference API with the built payload\nStep 5 — Code node parses and formats the raw API response into clean structured output\nStep 6 — Respond node returns the final result as JSON to the caller\n\nConfiguration Requirements\nHUGGING_FACE_API_KEY — Get free at huggingface.co/settings/tokens\nNo other credentials needed for basic usage\nOptional: Google Sheets credential for logging (node already included)\n\nSetup Guide\nStep 1: Import this workflow into your n8n instance\nStep 2: Open the Set API Config node and replace YOUR_HF_API_KEY with your token\nStep 3: Activate the workflow\nStep 4: POST to /webhook/hf-runner with your task payload\nStep 5: Swap models anytime by changing the model field in your request\n\nSample Webhook Payload\n{\n  \"task\": \"summarization\",\n  \"input\": \"Your long text goes here...\",\n  \"model\": \"\",\n  \"parameters\": {}\n}\n\nSupported Task Values\ntext_generation\nsummarization\nsentiment_analysis\ntranslation\nimage_generation\n\nDefault Models Used\ntext_generation    → mistralai/Mistral-7B-Instruct-v0.2\nsummarization      → facebook/bart-large-cnn\nsentiment_analysis → distilbert-base-uncased-finetuned-sst-2-english\ntranslation        → Helsinki-NLP/opus-mt-en-fr\nimage_generation   → stabilityai/stable-diffusion-xl-base-1.0",
  "nodes": [
    "n8n-nodes-base.httpRequest",
    "n8n-nodes-base.code"
  ],
  "tags": []
}