{
  "id": 12084,
  "name": "Research content keywords with SE Ranking and export to Google Sheets",
  "description": "\nWho is this for\nContent creators looking for topic ideas\nSEO specialists doing keyword research  \nMarketing teams planning content calendars\n\nWhat this workflow does\nDiscover keyword opportunities from 4 different sources (longtail, questions, similar, related) and export analyzed results to Google Sheets.\n\nWhat you'll get\nLongtail, question, similar, and related keyword variations\nOpportunity scores based on volume, difficulty, and CPC\nSearch intent classification (informational, commercial, transactional, navigational)\nContent type suggestions (how-to guide, listicle, comparison, etc.)\nTrend analysis with historical search volume data\nEstimated monthly traffic potential\nPriority ranking (HIGH/MEDIUM/LOW)\nSERP features analysis\nAll results automatically exported to Google Sheets\n\nHow it works\nFetches 4 types of keywords from SE Ranking (longtail, questions, similar, related)\nMerges and deduplicates all results\nAnalyzes each keyword with custom scoring algorithm\nCalculates opportunity scores (volume 40%, difficulty 40%, CPC 20%)\nDetects search intent and suggests content types\nExports enriched data to Google Sheets with 17 columns\n\nRequirements\nSE Ranking account with API access (Get one here)\nSE Ranking community node installed (Install from npm)\nGoogle Sheets account\n\nSetup steps\nInstall the SE Ranking community node\nAdd your SE Ranking API credentials\nConnect your Google Sheets account\nUpdate the seed keyword in all 4 SE Ranking nodes (default: \"digital marketing\")\nSelect or create a Google Sheet for export\n\nCustomization\nAdjust volumeFrom and difficultyTo filters in SE Ranking nodes for different opportunity ranges\nChange limit parameter to fetch more/fewer keywords per source (max 1000)\nModify opportunity score formula in the Code node (currently: volume 40%, difficulty 40%, CPC 20%)\nUpdate content type detection patterns to match your industry\nChange source parameter for different countries (us, uk, de, fr, etc.)",
  "nodes": [
    "n8n-nodes-base.googleSheets",
    "n8n-nodes-base.code"
  ],
  "tags": []
}