{
  "id": 10471,
  "name": "Self update Docker-based n8n with email approval and SSH",
  "description": "n8n Self-Updater Workflow\n\n&gt; An automated n8n workflow originally built for DigitalOcean-based n8n deployments, but fully compatible with any VPS or cloud hosting (e.g., AWS, Google Cloud, Hetzner, Linode, etc.) where n8n runs via Docker.\n\nThis workflow checks for the latest Docker image of n8n, notifies you via email for approval, and securely updates your n8n instance via SSH once approved.\n\nHow It Works\n\nTrigger: The workflow runs automatically every 3 days at 4 PM UTC (or manually if triggered).\nCheck Version: It retrieves your current n8n Docker version and image digest via SSH.\nCompare: Fetches the remote digest from Docker Hub and compares it with the local one.\nNotify via Email: If a new update is available, an approval email is sent with details:\n\n   Current version\n   Local digest\n   Remote digest\n   What will happen after approval\nApproval Logic:\n\n   Approve → Workflow connects via SSH and updates the n8n container automatically.\n   Decline → Workflow ends; next check occurs in the next cycle.\nAuto Update Execution:\n\n   Creates (if missing) a update_docker.sh script on the server.\n   Runs it in the background (nohup) to:\n\n          cd /opt/n8n-docker-caddy\n     docker compose pull\n     docker compose down\n     docker compose up -d\n        The delay ensures n8n restarts only after workflow completion.\n\nRequirements\n\nSSH Access** to your server (where n8n runs).\n\n  Add your credentials in n8n under Credentials → SSH Password.\nSMTP Connection** for email notifications.\n\n  Configure in Credentials → SMTP.\n  Fill in:\n\n    From Email → e.g., info@yourdomain.com\n    To Email → your email for receiving approvals\nDocker-based n8n Deployment**, e.g., n8n-docker-caddy setup.\nDocker and docker-compose** installed on the server.\n\nHow to Use\n\nImport the Workflow:\n\n   Copy the provided JSON file.\n   In your n8n instance → click Import Workflow → paste the JSON.\n\nSet Up Credentials:\n\n   Create two credentials in n8n:\n\n     SSH Password → Your server's SSH credentials.\n     SMTP → Your email provider's SMTP credentials.\n\nEdit the Email Node:\n\n   Replace:\n\n     fromEmail: info@yourdomain.com → with your email.\n     toEmail: youremail@yourdomain.com → with your desired recipient.\n\nEnable Auto Trigger (optional):\n\n   Go to the Schedule Trigger node and set your desired interval/time.\n\nRun the Workflow:\n\n   Test manually first.\n   Once verified, activate it for automatic checks.\n\nNotes\n\nOriginally designed for DigitalOcean VPS setups, but can run on any Docker-based n8n server.\nThe workflow avoids duplicate updates by comparing digests instead of version tags.\nIf the update_docker.sh file already exists, it reuses it safely.\nApproval emails include full details for transparency.\nBackground execution ensures no interruptions during restart.\n\nExample Behavior\n\nDay 1**: Workflow checks → detects update → sends email → user approves.\n30 seconds later**: Workflow runs update script → n8n restarts with latest Docker image.\nDay 4**: Workflow checks again → digests match → silently completes (no email sent).\n\nAuthor: Muhammad Anas Farooq\n",
  "nodes": [
    "n8n-nodes-base.emailSend",
    "n8n-nodes-base.httpRequest"
  ],
  "tags": []
}